odoo8_addon_business_requirement_deliverable_project_categ-8.0.1.0.0.99.dev4-py2.7-nspkg.pth
odoo8_addon_business_requirement_deliverable_project_categ-8.0.1.0.0.99.dev4.dist-info/METADATA
odoo8_addon_business_requirement_deliverable_project_categ-8.0.1.0.0.99.dev4.dist-info/RECORD
odoo8_addon_business_requirement_deliverable_project_categ-8.0.1.0.0.99.dev4.dist-info/WHEEL
odoo8_addon_business_requirement_deliverable_project_categ-8.0.1.0.0.99.dev4.dist-info/namespace_packages.txt
odoo8_addon_business_requirement_deliverable_project_categ-8.0.1.0.0.99.dev4.dist-info/top_level.txt
odoo_addons/business_requirement_deliverable_project_categ/README.rst
odoo_addons/business_requirement_deliverable_project_categ/__init__.py
odoo_addons/business_requirement_deliverable_project_categ/__openerp__.py
odoo_addons/business_requirement_deliverable_project_categ/i18n/business_requirement_deliverable_project_categ.pot
odoo_addons/business_requirement_deliverable_project_categ/i18n/sl.po
odoo_addons/business_requirement_deliverable_project_categ/static/description/icon.png
odoo_addons/business_requirement_deliverable_project_categ/wizard/__init__.py
odoo_addons/business_requirement_deliverable_project_categ/wizard/generate_projects.py
