Metadata-Version: 2.1
Name: odoo8-addon-business-requirement-deliverable-project-categ
Version: 8.0.1.0.0.99.dev4
Summary: Include category on generating project
Home-page: https://www.elico-corp.com
Author: Elico Corp, Odoo Community Association (OCA)
Author-email: support@odoo-community.org
License: AGPL-3
Platform: UNKNOWN
Classifier: Programming Language :: Python
Classifier: Framework :: Odoo
Classifier: License :: OSI Approved :: GNU Affero General Public License v3
Requires-Python: ~=2.7
Requires-Dist: odoo8-addon-business-requirement-deliverable-categ
Requires-Dist: odoo8-addon-business-requirement-deliverable-project
Requires-Dist: odoo (<9.0a,>=8.0a)
